[
  {
    "employer_name": "AI Jobs",
    "job_title": "Power Electronics Engineer – Battery Charger Development",
    "job_city": "Palo Alto",
    "job_state": "CA",
    "job_posted_at": "48min",
    "job_description": "• Required QualificationsBachelor’s or Master’s degree in Electrical Engineering or a related field.\n• 3+ years of experience in power electronics design, with a focus on battery charger, power supply development or inverter designStrong proficiency in simulation tools (e.\n• Hands-on experience with switch-mode power supplies (SMPS) and digital/analog control of converters.\n• Experience with lab equipment including oscilloscopes, power analyzers, electronic loads, and thermal chambers.\n• Preferred QualificationsExperience in systems over 60V and multi-kW charger design.\n• Background in EV charging, robotics, drones, or industrial energy systems.\n• Knowledge of functional safety, isolation requirements, and fail-safe system design.\n• Experience with design for EMC and compliance testing.",
    "job_apply_link": "https://www.aijobs.com/jobs/162926830-power-electronics-engineer-battery-charger-development",
    "id": "ai-jobs-power-electronics-engineer-battery-charger-development-palo-alto"
  }
]